briefcase_kivy_bootstrap/__init__.py
briefcase_kivy_bootstrap/py.typed
briefcase_kivy_bootstrap-1.0.0.post1.dist-info/licenses/LICENSE
briefcase_kivy_bootstrap-1.0.0.post1.dist-info/METADATA
briefcase_kivy_bootstrap-1.0.0.post1.dist-info/WHEEL
briefcase_kivy_bootstrap-1.0.0.post1.dist-info/entry_points.txt
briefcase_kivy_bootstrap-1.0.0.post1.dist-info/top_level.txt
briefcase_kivy_bootstrap-1.0.0.post1.dist-info/RECORD
