Metadata-Version: 2.4
Name: briefcase-kivy-bootstrap
Version: 1.0.0.post1
Summary: Kivy GUI framework bootstrap for Briefcase P4A backend - Tested integration for Android APK builds with Kivy
Author-email: Al pyCino <thealpycino@gmail.com>
Maintainer-email: Al pyCino <thealpycino@gmail.com>
License: MIT
Project-URL: Homepage, https://github.com/pyCino/briefcase-kivy-bootstrap
Project-URL: Documentation, https://github.com/pyCino/briefcase-kivy-bootstrap#readme
Project-URL: Repository, https://github.com/pyCino/briefcase-kivy-bootstrap.git
Project-URL: Issues, https://github.com/pyCino/briefcase-kivy-bootstrap/issues
Keywords: briefcase,kivy,gui,bootstrap,mobile,cross-platform
Classifier: Development Status :: 5 - Production/Stable
Classifier: Intended Audience :: Developers
Classifier: License :: OSI Approved :: MIT License
Classifier: Operating System :: OS Independent
Classifier: Programming Language :: Python :: 3
Classifier: Programming Language :: Python :: 3.8
Classifier: Programming Language :: Python :: 3.9
Classifier: Programming Language :: Python :: 3.10
Classifier: Programming Language :: Python :: 3.11
Classifier: Programming Language :: Python :: 3.12
Classifier: Topic :: Software Development :: Build Tools
Classifier: Topic :: Software Development :: Libraries :: Python Modules
Classifier: Topic :: System :: Software Distribution
Requires-Python: >=3.8
License-File: LICENSE
Requires-Dist: briefcase>=0.3.23
Requires-Dist: kivy>=2.3.1
Provides-Extra: dev
Requires-Dist: pytest>=7.0.0; extra == "dev"
Requires-Dist: pytest-cov>=4.0.0; extra == "dev"
Requires-Dist: black>=23.0.0; extra == "dev"
Requires-Dist: flake8>=6.0.0; extra == "dev"
Requires-Dist: mypy>=1.0.0; extra == "dev"
Dynamic: license-file
